distrilockper/__init__.py
distrilockper/connection_manager.py
distrilockper/expiration_factory.py
distrilockper/lock_helper.py
distrilockper/Executor/__init__.py
distrilockper/Executor/watch_dog_thread.py
distrilockper/config/ClusterServersConfig.py
distrilockper/config/SingleServerConfig.py
distrilockper/config/__init__.py
distrilockper/config/config.py
distrilockper/connection/BaseConnectionManager.py
distrilockper/connection/__init__.py
distrilockper/exception/__init__.py
distrilockper/lock_entry/__init__.py
distrilockper/misc/__init__.py
distrilockper/misc/exceptions.py
distrilockper/misc/lock_promisc.py
distrilockper/pubsub/__init__.py
distrilockper/pubsub/async_semaphore.py
distrilockper/pubsub/lock_pub_sub.py
distrilockper/pubsub/publish_subscribe.py
distrilockper/pubsub/pubsub_executor.py
distrilockper/pubsub/semaphore_pub_sub.py
distrilockper/services/__init__.py
distrilockper/services/publish_subscribe_service.py
distrilockper/util/Runnable.py
distrilockper/util/__init__.py
distrilockper/util/count_down_latch.py
distrilockper/util/linked_dictionary.py
distrilockper/util/linkedqueue.py
distrilockper/util/listener_holder.py
distrilockper/util/lock_entry.py
distrilockper/util/logger.py
distrilockper/util/redis_object.py
distrilockper/util/reentrant_lock.py
distrilockper/util/thread_safe_queue.py
distrilockper/util/thread_safe_set.py
playground/AtomicReference_playground.py
playground/__init__.py
playground/aredis_playground.py
playground/asyncio_redis_playground.py
playground/future_playground.py
playground/listener_playground.py
playground/overload_playground.py
playground/playground_printthreading.py
playground/redis_consumer_playground.py
playground/semaphore_palyground.py
playground/string_byte_playground.py
playground/string_byte_playground_1.py
playground/thread_pool_executor.py
playground/watchdog_play.py
testcase/__init__.py
testcase/interrupt.py
testcase/use_case_one.py
distrilockper-0.0.1a11.dist-info/LICENSE
distrilockper-0.0.1a11.dist-info/METADATA
distrilockper-0.0.1a11.dist-info/WHEEL
distrilockper-0.0.1a11.dist-info/top_level.txt
distrilockper-0.0.1a11.dist-info/RECORD
