Metadata-Version: 2.1
Name: distrilockper
Version: 0.0.1a11
Summary: Distributed Lock with using Redis
Home-page: https://gitlab.com/luislui/distributed_lock_helper
Author: Louis Lui
Author-email: luis11235178@gmail.com
License: MIT License
Keywords: Lock,Distributed
Platform: UNKNOWN
Classifier: Development Status :: 2 - Pre-Alpha
Classifier: Environment :: Console
Classifier: Intended Audience :: Developers
Classifier: License :: OSI Approved :: MIT License
Classifier: Operating System :: OS Independent
Classifier: Programming Language :: Python
Classifier: Programming Language :: Python :: 3
Classifier: Programming Language :: Python :: 3.5
Classifier: Programming Language :: Python :: 3.6
Classifier: Programming Language :: Python :: 3.7
Classifier: Programming Language :: Python :: 3.8
Classifier: Programming Language :: Python :: 3.9
Classifier: Topic :: Database
Requires-Dist: coloredlogs (~=14.0)
Requires-Dist: uuid (~=1.30)
Requires-Dist: redis (~=3.0.1)
Requires-Dist: python-json-logger
Requires-Dist: redis-py-cluster
Requires-Dist: atomos
Requires-Dist: nest-asyncio
Requires-Dist: multipledispatch
Requires-Dist: pebble
